{
  "type" : "FeatureCollection",
  "crs" : {
    "type" : "name",
    "properties" : {
      "name" : "EPSG:4326"
    }
  },
  "features" : [
    {
      "type" : "Feature",
      "id" : 0,
      "geometry" : {
        "type" : "Polygon",
        "coordinates" : [
          [
            [
              85.536756512150419,
              27.617597850913
            ],
            [
              85.536868822709891,
              27.617700643628496
            ],
            [
              85.536870726278721,
              27.617845314857618
            ],
            [
              85.536746994306327,
              27.61796143255475
            ],
            [
              85.53657757668276,
              27.617970950398671
            ],
            [
              85.536457651848082,
              27.617870061252063
            ],
            [
              85.536470976829719,
              27.617719679316508
            ],
            [
              85.536590901664397,
              27.617605465188262
            ],
            [
              85.536756512150419,
              27.617597850913
            ]
          ]
        ]
      },
      "properties" : {
        "FID" : 0,
        "Id" : 1,
        "name" : "KU Boys Hostel"
      }
    },
    {
      "type" : "Feature",
      "id" : 1,
      "geometry" : {
        "type" : "Polygon",
        "coordinates" : [
          [
            [
              85.536181634371303,
              27.617910036197031
            ],
            [
              85.536189248646508,
              27.617729197160656
            ],
            [
              85.536427194747205,
              27.617753943555101
            ],
            [
              85.536419580471943,
              27.61793287902276
            ],
            [
              85.536181634371303,
              27.617910036197031
            ]
          ]
        ]
      },
      "properties" : {
        "FID" : 1,
        "Id" : 0,
        "name" : "Social Hall"
      }
    },
    {
      "type" : "Feature",
      "id" : 2,
      "geometry" : {
        "type" : "Polygon",
        "coordinates" : [
          [
            [
              85.537242398087812,
              27.617598564751404
            ],
            [
              85.53709963042752,
              27.617574770141232
            ],
            [
              85.537084758796141,
              27.617393336239502
            ],
            [
              85.537239423761605,
              27.617408207870938
            ],
            [
              85.537242398087812,
              27.617598564751404
            ]
          ]
        ]
      },
      "properties" : {
        "FID" : 2,
        "Id" : 2,
        "name" : "TTC Boys Hostel"
      }
    },
    {
      "type" : "Feature",
      "id" : 3,
      "geometry" : {
        "type" : "MultiPolygon",
        "coordinates" : [
          [
            [
              [
                85.537855109296856,
                27.618249942201714
              ],
              [
                85.537852134970649,
                27.618246967875507
              ],
              [
                85.537854443274739,
                27.618247171549342
              ],
              [
                85.537855109296856,
                27.618249942201714
              ]
            ]
          ],
          [
            [
              [
                85.537854443274739,
                27.618247171549342
              ],
              [
                85.537780751140417,
                27.617940612270957
              ],
              [
                85.537911621495653,
                27.617931689292163
              ],
              [
                85.537980030999677,
                27.61816963539269
              ],
              [
                85.538027620219736,
                27.618157738087632
              ],
              [
                85.538054389156116,
                27.618264813832923
              ],
              [
                85.537854443274739,
                27.618247171549342
              ]
            ]
          ]
        ]
      },
      "properties" : {
        "FID" : 3,
        "Id" : 3,
        "name" : "KU Messs II"
      }
    }
  ]
}